infi.os_info-0.1.13-py3.7-nspkg.pth
infi/os_info/__init__.py
infi/os_info/__version__.py
infi/os_info/parse_version.py
infi/os_info/platform.py
infi/os_info/scripts.py
infi.os_info-0.1.13.dist-info/LICENSE
infi.os_info-0.1.13.dist-info/METADATA
infi.os_info-0.1.13.dist-info/WHEEL
infi.os_info-0.1.13.dist-info/entry_points.txt
infi.os_info-0.1.13.dist-info/namespace_packages.txt
infi.os_info-0.1.13.dist-info/top_level.txt
infi.os_info-0.1.13.dist-info/RECORD
